setup.py
munchlax/__init__.py
munchlax/bot.py
munchlax/slack.py
munchlax/slackerror.py
munchlax.egg-info/PKG-INFO
munchlax.egg-info/SOURCES.txt
munchlax.egg-info/dependency_links.txt
munchlax.egg-info/not-zip-safe
munchlax.egg-info/requires.txt
munchlax.egg-info/top_level.txt
munchlax/lib/__init__.py
munchlax/lib/async.py
munchlax/lib/channel.py
munchlax/lib/comment.py
munchlax/lib/file.py
munchlax/lib/group.py
munchlax/lib/im.py
munchlax/lib/message.py
munchlax/lib/method.py
munchlax/lib/mpim.py
munchlax/lib/object.py
munchlax/lib/user.py