Metadata-Version: 1.0
Name: munchlax
Version: 0.1.4
Summary: Asynchronous Slack library for Python 3.4+
Home-page: https://github.com/WildAndrewLee/Munchlax
Author: reticence
Author-email: andrew@reticent.io
License: WTFPL
Platform: UNKNOWN
